{
  "recipe": {
    "appcast": {
      "checkpoint": null,
      "url": null
    },
    "bundle": "4K Video Downloader.app",
    "ci": "true",
    "dir": "/Applications",
    "download": "https://dl.4kdownload.com/app/4kvideodownloader_4.16.4.dmg?source=website",
    "id": "4kvideodownloader",
    "identifier": "com.openmedia.4kvideodownloader",
    "processes": [],
    "sha256": "161ccf7116690a5ebf02d39a6218afb7f49858d14bfdeced5f008365abbd01e9",
    "symlink": null,
    "version": "4.16.4",
    "web": "https://www.4kdownload.com/products/product-videodownloader"
  }
}
