{
  "recipe": {
    "id": "abstract",
    "bundle": "Abstract.app",
    "identifier": "com.elasticprojects.abstract-desktop",
    "download": "https://downloads.goabstract.com/mac/Abstract-91.0.2.dmg",
    "sha256": "a3165b4f9a728c9f81ca3d055c892568f8e835643020faf0548f5db15c0adc89",
    "appcast": {
      "url": "https://www.goabstract.com/release-notes/",
      "checkpoint": "2729197eeb6ed9f39fb4d133d4a2710ef938de65fac67e7ececa6bb31e9314f6"
    },
    "version": "91.0.2",
    "build": null,
    "dir": "/Applications",
    "symlink": null,
    "web": "https://www.abstract.com/"
  }
}
