{
  "recipe": {
    "id": "abstract",
    "bundle": "Abstract.app",
    "identifier": "com.elasticprojects.abstract-desktop",
    "download": "https://downloads.goabstract.com/mac/Abstract-91.0.0.dmg",
    "sha256": "509c1f86b5acb8cf53fec3b527fe7c8a47fd15a5e51eb8dfb010bc130e77e5ca",
    "appcast": {
      "url": "https://www.goabstract.com/release-notes/",
      "checkpoint": "53fcac8fdb71c387c28c5b2ada0bd1f461d5766c7140e8cddf33b32c1faaf8f3"
    },
    "version": "91.0.0",
    "build": null,
    "dir": "/Applications",
    "symlink": null,
    "web": "https://www.abstract.com/"
  }
}
