{
  "recipe": {
    "id": "adobereaderdc",
    "bundle": "Adobe Acrobat Reader DC.app",
    "identifier": "com.adobe.Reader",
    "download": "https://ardownload2.adobe.com/pub/adobe/reader/mac/AcrobatDC/1801120055/AcroRdrDC_1801120055_MUI.dmg",
    "sha256": "dd7e15fc8785b218c674c151b46a2349c6ca8f9df8d97f1b48a33905be60decc",
    "appcast": {
        "url": null,
        "checkpoint": null
    },
    "version": "18.011.20055",
    "build": null,
    "dir": "/Applications",
    "symlink": null,
    "web": "https://acrobat.adobe.com/us/en/acrobat/pdf-reader.html"
  }
}
