{
  "recipe": {
    "id": "anki",
    "bundle": "Anki.app",
    "identifier": "net.ankiweb.dtop",
    "download": "https://github.com/ankitects/anki/releases/download/2.1.26/anki-2.1.26-mac.dmg",
    "sha256": "a824b0cb3145148f88d438f218c78cb5abf06ef7d96a94d025c649e4760ce1aa",
    "appcast": {
      "url": "https://changes.ankiweb.net/README.md",
      "checkpoint": "12982a28cdaf6f08ec88e76c78a74a09463949b841f6b0cd1315f08a7ba41f96"
    },
    "version": "2.1.26",
    "build": null,
    "dir": "/Applications",
    "symlink": null,
    "web": "https://apps.ankiweb.net/"
  }
}
