{
  "recipe": {
    "id": "atom",
    "bundle": "Atom.app",
    "identifier": "com.github.atom",
    "download": "https://atom-installer.github.com/v1.28.1/atom-mac.zip",
    "sha256": "8722cbe2f11180d7891971c4c316f543bcba83b6a2fe1c2cdc9a61b0f98ade46",
    "appcast": {
        "url": "https://github.com/atom/atom/releases.atom",
        "checkpoint": "02fe33b7efe44e8b5ffe1e5071d6d39e8fd9a42aeef92b82c8874de1c13c17d8"
    },
    "version": "1.28.1",
    "build": null,
    "dir": "/Applications",
    "symlink": null,
    "web": "https://atom.io/"
  }
}
