{
  "recipe": {
    "id": "autodeskfusion360",
    "bundle": "Autodesk Fusion 360.app",
    "identifier": "com.autodesk.edu.fusion360",
    "download": "https://dl.appstreaming.autodesk.com/production/installers/Autodesk%20Fusion%20360%20Admin%20Install.pkg",
    "sha256": "d43ba53aef5d587201b086d700f0392bd4a349936f7d91e2ea96075da3f75d15",
    "appcast": {
      "url": null,
      "checkpoint": null
    },
    "version": "2.0.9142",
    "build": null,
    "dir": "/Applications",
    "symlink": null,
    "web": "https://www.autodesk.com/products/fusion-360",
    "ci": "true"
  }
}
