{
  "recipe": {
    "id": "balenaetcher",
    "bundle": "balenaEtcher.app",
    "identifier": "io.balena.etcher",
    "download": "https://github.com/balena-io/etcher/releases/download/v1.5.110/balenaEtcher-1.5.110.dmg",
    "sha256": "f246e9fc6c619a4d8fbdd4ee69eb4a8ac15171554ae3d25f2400b041bec50f67",
    "appcast": {
      "url": null,
      "checkpoint": null
    },
    "version": "1.5.110",
    "build": null,
    "dir": "/Applications",
    "symlink": null,
    "web": "https://balena.io/etcher",
    "ci": "true"
  }
}
