{
  "recipe": {
    "id": "balenaetcher",
    "bundle": "balenaEtcher.app",
    "identifier": "io.balena.etcher",
    "download": "https://github.com/balena-io/etcher/releases/download/v1.5.63/balenaEtcher-1.5.63.dmg",
    "sha256": "59f98032491f131210609257571cfe490cac980a97b306f745c40fe69b7e3bde",
    "appcast": {
      "url": "https://github.com/balena-io/etcher/releases.atom",
      "checkpoint": "b78cf08ee71c78e53fcf69a849e0bea8072877b1b9ddabbc5f7f6467ba74e3fc"
    },
    "version": "1.5.63",
    "build": null,
    "dir": "/Applications",
    "symlink": null,
    "web": "https://balena.io/etcher"
  }
}
