{
  "recipe": {
    "id": "caffeine",
    "bundle": "Caffeine.app",
    "identifier": "com.lightheadsw.Caffeine",
    "download": "https://cl.ly/2d0e01d909e4/download/Caffeine.dmg",
    "sha256": "7c56f8f679d69d3c9f81fd90af79949e8ebf8d1a2d60c6af29350214b641e381",
    "appcast": {
      "url": null,
      "checkpoint": null
    },
    "version": "1.1.2",
    "build": null,
    "dir": "/Applications",
    "safequit": "false",
    "symlink": null,
    "web": "http://lightheadsw.com/caffeine/",
    "ci": "true"
  }
}
