{
  "recipe": {
    "appcast": {
      "checkpoint": null,
      "url": null
    },
    "bundle": "Camtasia 2021.app",
    "ci": "true",
    "dir": "/Applications",
    "download": "https://download.techsmith.com/camtasiamac/releases/Camtasia.dmg",
    "id": "camtasia",
    "identifier": "com.techsmith.camtasia2021",
    "processes": [],
    "sha256": "3280d39a86f6de5e3019f9334718d3e73744c061a77608c4add4566c39ed359f",
    "symlink": null,
    "version": "2021.0.2",
    "web": "https://www.techsmith.com/camtasia.html"
  }
}
