{
  "recipe": {
    "id": "carboncopycloner",
    "bundle": "Carbon Copy Cloner.app",
    "identifier": "com.bombich.ccc",
    "download": "https://bombich.scdn1.secure.raxcdn.com/software/files/ccc-5.1.1.5406.zip",
    "sha256": "bdf86295db0dcd6acccb3cc7e770f281e5e1b0ada94fb9de5b6360bfdd93a244",
    "appcast": {
        "url": null,
        "checkpoint": null
    },
    "version": "5.1.1",
    "build": "5406",
    "dir": "/Applications",
    "symlink": null,
    "web": "https://bombich.com/"
  }
}
