{
  "recipe": {
    "id": "chromium",
    "bundle": "Chromium.app",
    "identifier": "org.chromium.Chromium",
    "download": "https://commondatastorage.googleapis.com/chromium-browser-snapshots/Mac/783459/chrome-mac.zip",
    "sha256": "b860726ae09262edb9321ef78b2067363af3b6a6f156a53deb23b30ecfdfe880",
    "appcast": {
      "url": null,
      "checkpoint": null
    },
    "version": "86.0.4187.0",
    "build": null,
    "dir": "/Applications",
    "symlink": null,
    "web": "https://www.chromium.org/",
    "ci": "true"
  }
}
