{
  "recipe": {
    "id": "chromium",
    "bundle": "Chromium.app",
    "identifier": "org.chromium.Chromium",
    "download": "https://commondatastorage.googleapis.com/chromium-browser-snapshots/Mac/804867/chrome-mac.zip",
    "sha256": "8c0bb393d2a29831d784553b328548d8d960e9261679ab340d501aebaade26df",
    "appcast": {
      "url": null,
      "checkpoint": null
    },
    "version": "87.0.4259.0",
    "build": null,
    "dir": "/Applications",
    "symlink": null,
    "web": "https://www.chromium.org/",
    "ci": "true"
  }
}
