{
  "recipe": {
    "id": "chromium",
    "bundle": "Chromium.app",
    "identifier": "org.chromium.Chromium",
    "download": "https://commondatastorage.googleapis.com/chromium-browser-snapshots/Mac/817687/chrome-mac.zip",
    "sha256": "304e0e1bd9d5ca354ad2d7b8412a6df7a5e2be3c834105ced5bbb7cc2aef68c1",
    "appcast": {
      "url": null,
      "checkpoint": null
    },
    "version": "88.0.4294.0",
    "build": null,
    "dir": "/Applications",
    "symlink": null,
    "web": "https://www.chromium.org/",
    "ci": "true"
  }
}
