{
  "recipe": {
    "id": "chromium",
    "bundle": "Chromium.app",
    "identifier": "org.chromium.Chromium",
    "download": "https://commondatastorage.googleapis.com/chromium-browser-snapshots/Mac/854866/chrome-mac.zip",
    "sha256": "5468c8f40ca6d788aec964eb55da6e1153a48aad2ed62bfe8f18abd3d2079360",
    "appcast": {
      "url": null,
      "checkpoint": null
    },
    "version": "90.0.4422.0",
    "build": null,
    "dir": "/Applications",
    "symlink": null,
    "web": "https://www.chromium.org/",
    "ci": "true"
  }
}
