{
  "recipe": {
    "id": "chromium",
    "bundle": "Chromium.app",
    "identifier": "org.chromium.Chromium",
    "download": "https://commondatastorage.googleapis.com/chromium-browser-snapshots/Mac/839956/chrome-mac.zip",
    "sha256": "7c1e292118a0b724fab13bdf4a7ca1ae45ee899d16c3e7244f131b977d1dcf8c",
    "appcast": {
      "url": null,
      "checkpoint": null
    },
    "version": "89.0.4377.0",
    "build": null,
    "dir": "/Applications",
    "symlink": null,
    "web": "https://www.chromium.org/",
    "ci": "true"
  }
}
