{
  "recipe": {
    "id": "chromium",
    "bundle": "Chromium.app",
    "identifier": "org.chromium.Chromium",
    "download": "https://commondatastorage.googleapis.com/chromium-browser-snapshots/Mac/870935/chrome-mac.zip",
    "sha256": "1040d9dbb018f37272e79e6f67eab9becf07068e5cb4fc8ec05386be8c38d5bd",
    "appcast": {
      "url": null,
      "checkpoint": null
    },
    "version": "92.0.4473.0",
    "build": null,
    "dir": "/Applications",
    "symlink": null,
    "web": "https://www.chromium.org/",
    "ci": "true"
  }
}
