{
  "recipe": {
    "id": "chromium",
    "bundle": "Chromium.app",
    "identifier": "org.chromium.Chromium",
    "download": "https://commondatastorage.googleapis.com/chromium-browser-snapshots/Mac/866802/chrome-mac.zip",
    "sha256": "7b180d92670b4d0a246db4a766062f16b5ed40fbfc64c1f5ccac5fb738a73bf1",
    "appcast": {
      "url": null,
      "checkpoint": null
    },
    "version": "91.0.4459.0",
    "build": null,
    "dir": "/Applications",
    "symlink": null,
    "web": "https://www.chromium.org/",
    "ci": "true"
  }
}
