{
  "recipe": {
    "id": "chromium",
    "bundle": "Chromium.app",
    "identifier": "org.chromium.Chromium",
    "download": "https://commondatastorage.googleapis.com/chromium-browser-snapshots/Mac/806519/chrome-mac.zip",
    "sha256": "a37c9f65ce53a481e37a86dc7e4b333294929eec02b6998a5f3f57675a208439",
    "appcast": {
      "url": null,
      "checkpoint": null
    },
    "version": "87.0.4263.0",
    "build": null,
    "dir": "/Applications",
    "symlink": null,
    "web": "https://www.chromium.org/",
    "ci": "true"
  }
}
