{
  "recipe": {
    "id": "chromium",
    "bundle": "Chromium.app",
    "identifier": "org.chromium.Chromium",
    "download": "https://commondatastorage.googleapis.com/chromium-browser-snapshots/Mac/836433/chrome-mac.zip",
    "sha256": "16affd91d80f2501f5ed2f7b50b870bc14f6d758303b26e03737b746c5ace759",
    "appcast": {
      "url": null,
      "checkpoint": null
    },
    "version": "89.0.4354.0",
    "build": null,
    "dir": "/Applications",
    "symlink": null,
    "web": "https://www.chromium.org/",
    "ci": "true"
  }
}
