{
  "recipe": {
    "id": "chromium",
    "bundle": "Chromium.app",
    "identifier": "org.chromium.Chromium",
    "download": "https://commondatastorage.googleapis.com/chromium-browser-snapshots/Mac/786673/chrome-mac.zip",
    "sha256": "e0ab172f2ab40fc5e863996b99d8056edd934ebc90e773e353682b61cd1f2999",
    "appcast": {
      "url": null,
      "checkpoint": null
    },
    "version": "86.0.4198.0",
    "build": null,
    "dir": "/Applications",
    "symlink": null,
    "web": "https://www.chromium.org/",
    "ci": "true"
  }
}
