{
  "recipe": {
    "appcast": {
      "checkpoint": null,
      "url": null
    },
    "bundle": "Chromium.app",
    "ci": "true",
    "dir": "/Applications",
    "download": "https://commondatastorage.googleapis.com/chromium-browser-snapshots/Mac/889813/chrome-mac.zip",
    "id": "chromium",
    "identifier": "org.chromium.Chromium",
    "processes": null,
    "sha256": "58f4131ce8238dc9aa62260f19a3acbb6b040d6eb8343ac89f103cd67c4d31b7",
    "symlink": null,
    "version": "93.0.4536.0",
    "web": "https://www.chromium.org/"
  }
}
