{
  "recipe": {
    "id": "chromium",
    "bundle": "Chromium.app",
    "identifier": "org.chromium.Chromium",
    "download": "https://commondatastorage.googleapis.com/chromium-browser-snapshots/Mac/837869/chrome-mac.zip",
    "sha256": "4b6d5575eb3d7424a8d08ab6ed3854cc44bc953bb119637f6333b5f97109b017",
    "appcast": {
      "url": null,
      "checkpoint": null
    },
    "version": "89.0.4358.0",
    "build": null,
    "dir": "/Applications",
    "symlink": null,
    "web": "https://www.chromium.org/",
    "ci": "true"
  }
}
