{
  "recipe": {
    "appcast": {
      "checkpoint": null,
      "url": null
    },
    "bundle": "Chromium.app",
    "ci": "true",
    "dir": "/Applications",
    "download": "https://commondatastorage.googleapis.com/chromium-browser-snapshots/Mac/899147/chrome-mac.zip",
    "id": "chromium",
    "identifier": "org.chromium.Chromium",
    "processes": [],
    "sha256": "a4810a2fb210b6f4c8b6ed10d13c03bb29d51d51ffa609482830a29f076e01f1",
    "symlink": null,
    "version": "93.0.4569.0",
    "web": "https://www.chromium.org/"
  }
}
