{
  "recipe": {
    "id": "chromium",
    "bundle": "Chromium.app",
    "identifier": "org.chromium.Chromium",
    "download": "https://commondatastorage.googleapis.com/chromium-browser-snapshots/Mac/778913/chrome-mac.zip",
    "sha256": "be55f4ddb4d527b601e68d2ec3c3247bb3ea4af212bc6f1abcee988174fa1b49",
    "appcast": {
      "url": null,
      "checkpoint": null
    },
    "version": "85.0.4175.0",
    "build": null,
    "dir": "/Applications",
    "symlink": null,
    "web": "https://www.chromium.org/",
    "ci": "true"
  }
}
