{
  "recipe": {
    "appcast": {
      "checkpoint": null,
      "url": null
    },
    "bundle": "Chromium.app",
    "ci": "true",
    "dir": "/Applications",
    "download": "https://commondatastorage.googleapis.com/chromium-browser-snapshots/Mac/902865/chrome-mac.zip",
    "id": "chromium",
    "identifier": "org.chromium.Chromium",
    "processes": [],
    "sha256": "0a2a269a592dca74841e091cf8058b092ed7a449164c0215cd810609f7aeaa60",
    "symlink": null,
    "version": "94.0.4580.0",
    "web": "https://www.chromium.org/"
  }
}
