{
  "recipe": {
    "id": "chromium",
    "bundle": "Chromium.app",
    "identifier": "org.chromium.Chromium",
    "download": "https://commondatastorage.googleapis.com/chromium-browser-snapshots/Mac/813254/chrome-mac.zip",
    "sha256": "a68bb0f3a67564068a5a9f009d2baa22fe8d201a523ed36a2982d29d821c1241",
    "appcast": {
      "url": null,
      "checkpoint": null
    },
    "version": "88.0.4281.0",
    "build": null,
    "dir": "/Applications",
    "symlink": null,
    "web": "https://www.chromium.org/",
    "ci": "true"
  }
}
