{
  "recipe": {
    "id": "chromium",
    "bundle": "Chromium.app",
    "identifier": "org.chromium.Chromium",
    "download": "https://commondatastorage.googleapis.com/chromium-browser-snapshots/Mac/822926/chrome-mac.zip",
    "sha256": "c0c750576f71193a1447224f363f17ed7eb857fa269662b685762f8337475dee",
    "appcast": {
      "url": null,
      "checkpoint": null
    },
    "version": "88.0.4310.0",
    "build": null,
    "dir": "/Applications",
    "symlink": null,
    "web": "https://www.chromium.org/",
    "ci": "true"
  }
}
