{
  "recipe": {
    "id": "dbeaver",
    "bundle": "DBeaver.app",
    "identifier": "org.jkiss.dbeaver.core.product",
    "download": "https://github.com/dbeaver/dbeaver/releases/download/6.3.4/dbeaver-ce-6.3.4-macos.dmg",
    "sha256": "18d7941cde96136fc0c36aa5ad4d5412b88955a322449500ef517c565edd9454",
    "appcast": {
        "url": "https://github.com/dbeaver/dbeaver/releases.atom",
      "checkpoint": "05a5a2e3833ed017e3b8c32c4e28e44e2156afb994c0ca69f7159bd2a85aba73"
    },
    "version": "6.3.4",
    "build": null,
    "dir": "/Applications",
    "symlink": null,
    "web": "https://dbeaver.io/"
  }
}
