{
  "recipe": {
    "id": "easyfind",
    "bundle": "EasyFind.app",
    "identifier": "org.grunenberg.EasyFind",
    "download": "https://download.devontechnologies.com/download/freeware/easyfind/5.0/EasyFind.app.zip",
    "sha256": "a389fc3c35a7d5111960c4ce5e631ad3b99ed1dd5534299b577a68cbd06bc327",
    "appcast": {
      "url": "https://www.devontechnologies.com/apps/freeware",
      "checkpoint": "4f03b80409a4502b541fbc8a3cdf74fad445993d02f64383a66f6f5dc0a3e4d5"
    },
    "version": "5.0",
    "build": null,
    "dir": "/Applications",
    "symlink": null,
    "web": "https://www.devontechnologies.com/apps/freeware"
  }
}
