{
  "recipe": {
    "id": "filezilla",
    "bundle": "FileZilla.app",
    "identifier": "org.filezilla-project.filezilla",
    "download": "https://aky-assets.s3.eu-central-1.wasabisys.com/FileZilla-3.51.0.pkg",
    "sha256": "4f62dd4406d1643d76034dc23277fa03afd041f435ef78615a38796d62c8536f",
    "appcast": {
      "url": null,
      "checkpoint": null
    },
    "version": "3.51.0",
    "build": null,
    "dir": "/Applications",
    "symlink": null,
    "web": "https://filezilla-project.org/",
    "ci": "true",
    "internal": "true"
  }
}
