{
  "recipe": {
    "id": "filezilla",
    "bundle": "FileZilla.app",
    "identifier": "org.filezilla-project.filezilla",
    "download": "https://dl4.cdn.filezilla-project.org/client/FileZilla_3.50.0_macosx-x86.app.tar.bz2?h=MEDxZ9xiU90o0VHIrdHR5w&x=1601612538",
    "sha256": "22d32e0439047186def741ec15cad748e33c05d5d192c65ffd96286eff1efd00",
    "appcast": {
      "url": null,
      "checkpoint": null
    },
    "version": "3.50.0",
    "build": null,
    "dir": "/Applications",
    "symlink": null,
    "web": "https://filezilla-project.org/",
    "ci": "true"
  }
}
