{
  "recipe": {
    "id": "firefox",
    "bundle": "Firefox.app",
    "identifier": "org.mozilla.firefox",
    "processes": [
      "firefox"
    ],
    "download": "http://releases.mozilla.org/pub/firefox/releases/84.0.2/mac/de/Firefox%2084.0.2.pkg",
    "sha256": "d545727181e84fb8de628c1f2c56ec9161db922b81e940645c2e35f8712fc32c",
    "appcast": {
      "url": null,
      "checkpoint": null
    },
    "version": "84.0.2",
    "build": null,
    "dir": "/Applications",
    "symlink": null,
    "web": "https://www.mozilla.org/firefox/",
    "ci": "true"
  }
}
