{
  "recipe": {
    "id": "firefox",
    "bundle": "Firefox.app",
    "identifier": "org.mozilla.firefox",
    "download": "https://download-installer.cdn.mozilla.net/pub/firefox/releases/59.0.3/mac/de/Firefox%2059.0.3.dmg",
    "sha256": "0dc106e52c1aea513cd8fb97d03c658e154789f292d8faa5a20e09a26cc80f47",
    "appcast": {
        "url": null,
        "checkpoint": null
    },
    "version": "59.0.3",
    "build": null,
    "dir": "/Applications",
    "symlink": null,
    "web": "https://www.mozilla.org/firefox/"
  }
}
