{
  "recipe": {
    "id": "fontexplorerxpro",
    "bundle": "FontExplorer X Pro.app",
    "identifier": "com.linotype.FontExplorerX",
    "download": "https://fex.linotype.com/download/mac/FontExplorerXPro.dmg",
    "sha256": "9b275bb36d51943b93ff226c317d8caaf62d7e58b885614bbc5b1bc6d5ff02c2",
    "appcast": {
      "url": null,
      "checkpoint": null
    },
    "version": "7.2.5",
    "build": null,
    "dir": "/Applications",
    "symlink": null,
    "web": "https://www.fontexplorerx.com/",
    "ci": "true"
  }
}
