{
  "recipe": {
    "appcast": {
      "checkpoint": null,
      "url": null
    },
    "bundle": "Google Chrome Canary.app",
    "ci": "true",
    "dir": "/Applications",
    "download": "https://dl.google.com/release2/q/canary/googlechrome.dmg",
    "id": "googlechromecanary",
    "identifier": "com.google.Chrome.canary",
    "processes": [],
    "sha256": "368778a719c0840d851fa33861ee06b281300cc5c83184afa17328515f011125",
    "symlink": null,
    "version": "93.0.4574.2",
    "web": "https://www.google.com/intl/en/chrome/canary/"
  }
}
