{
  "recipe": {
    "id": "googlechromecanary",
    "bundle": "Google Chrome Canary.app",
    "identifier": "com.google.Chrome.canary",
    "download": "https://dl.google.com/release2/q/canary/googlechrome.dmg",
    "sha256": "2b0131242b12423bdf1b7d8ceac57c73747d6385311cf6b52402d801988d10f8",
    "appcast": {
      "url": null,
      "checkpoint": null
    },
    "version": "88.0.4315.3",
    "build": null,
    "dir": "/Applications",
    "symlink": null,
    "web": "https://www.google.com/intl/en/chrome/canary/",
    "ci": "true"
  }
}
