{
  "recipe": {
    "appcast": {
      "checkpoint": null,
      "url": null
    },
    "bundle": "HIN Talk PP.app",
    "ci": "true",
    "dir": "/Applications",
    "download": "https://basepackages.vnc.biz/electron-dev/HIN%20Talk%20PP-latest.dmg",
    "id": "hintalkpp",
    "identifier": "biz.vnc.vnctalk.hintalk.desktop",
    "processes": [],
    "sha256": "803b187c62f953a91b0b6d08add6523b8f8abbabe2de5af24a2ca7a6c92e09ce",
    "symlink": null,
    "version": "2021062301",
    "web": null
  }
}
