{
  "recipe": {
    "id": "i1studio",
    "bundle": "i1Studio.app",
    "identifier": "com.x-rite.i1Studio",
    "download": "http://downloads.xrite.com/downloads/software/i1Studio/v1.1.1/mac/i1Studio.zip",
    "sha256": "74fc96c0b53dde1c2d6930cd549c720489f3e0f8eb3167a11494343d29d603ae",
    "appcast": {
      "url": null,
      "checkpoint": null
    },
    "version": "1.1.1",
    "build": null,
    "dir": "/Applications/i1Studio",
    "symlink": null,
    "web": "https://www.xrite.com/service-support/product-support/calibration-solutions/i1studio",
    "postflight": null
  }
}
