{
  "recipe": {
    "id": "lehrerofficedbadmin",
    "bundle": "LehrerOffice-DBAdmin.app",
    "identifier": "ch.rothsoft.sqlserver.cubesql.dbadmin",
    "download": "https://www.lehreroffice.ch/lo/dateien/db/lo_dbadmin_macos.dmg",
    "sha256": "a095e8e8bd6c49882902f0c47b05c54d5362ea5492bc5f607eedc61dee1fcd54",
    "appcast": {
      "url": null,
      "checkpoint": null
    },
    "version": "2020.1.0",
    "build": null,
    "dir": "/Applications/LehrerOffice",
    "symlink": null,
    "web": "https://www.lehreroffice.ch/",
    "ci": "true"
  }
}
