{
  "recipe": {
    "id": "lehrerofficezusatz",
    "bundle": "LehrerOffice Zusatz.app",
    "identifier": "ch.rothsoft.lehreroffice.sv",
    "download": "https://www.lehreroffice.ch/lo/dateien/zusatz/lo_zusatz_osx.dmg",
    "sha256": "8bde8bb65f1fa3c6544502b5e7c7baa40d66b3b4446cd95fcefea9fc31916228",
    "appcast": {
        "url": "https://www.lehreroffice.ch/services/update/getcurrentversion.php?app=Zusatz",
        "checkpoint": "5ba4d4a0c1354eee4400a738e53bc9db6e4c85a54c086f403b74d1a684956b35"
    },
    "version": "2018.7.0",
    "build": null,
    "dir": "/Applications/LehrerOffice",
    "symlink": null,
    "web": "https://www.lehreroffice.ch/"
  }
}
