{
  "recipe": {
    "id": "lehrerofficezusatz",
    "bundle": "LehrerOffice Zusatz.app",
    "identifier": "ch.rothsoft.lehreroffice.sv",
    "download": "https://download.lehrerofficeweb.ch/dateien/zusatz/lo_zusatz_macos.zip",
    "sha256": "befb8001642fbed2dd136b7f2b92b3cfb55ddd99969e63d6afd882f89865da19",
    "appcast": {
      "url": "https://www.lehreroffice.ch/services/update/getcurrentversion.php?app=Zusatz",
      "checkpoint": "4dc2aadae76a7b637f275e912efbc1abc7a177c160a8437cce4beab95b34f8af"
    },
    "version": "2020.3.1",
    "build": null,
    "dir": "/Applications/LehrerOffice",
    "symlink": null,
    "web": "https://www.lehreroffice.ch/"
  }
}
