{
  "recipe": {
    "id": "libreoffice",
    "bundle": "LibreOffice.app",
    "identifier": "org.libreoffice.script",
    "download": "https://download.documentfoundation.org/libreoffice/stable/6.4.0/mac/x86_64/LibreOffice_6.4.0_MacOS_x86-64.dmg",
    "sha256": "32e7af23282b6241f580d41f22114daa82a4adf96b817c87f68605743ea423cd",
    "appcast": {
      "url": "https://download.documentfoundation.org/libreoffice/stable/6.4.0/mac/x86_64/",
      "checkpoint": "683142b1610f8259bbf795f6e88ea187e843336372234324d5b1ad86ee4f11c5"
    },
    "version": "6.4.3",
    "build": null,
    "dir": "/Applications",
    "symlink": null,
    "web": "https://www.libreoffice.org/"
  }
}
