{
  "recipe": {
    "id": "macpass",
    "bundle": "MacPass.app",
    "identifier": "com.hicknhacksoftware.MacPass",
    "download": "https://github.com/MacPass/MacPass/releases/download/0.7.9/MacPass-0.7.9.zip",
    "sha256": "cb4445fad7f2e64726cbaa320b228dadb3b48afe15f138ae90600e912093f12c",
    "appcast": {
      "url": "https://github.com/MacPass/MacPass/releases.atom",
      "checkpoint": "4d4985856b7b6af1f69c3090278c47aa8f8ff9bff8d1d8419af13526be88ab22"
    },
    "version": "0.7.9",
    "build": null,
    "dir": "/Applications",
    "symlink": null,
    "web": "https://macpass.github.io/"
  }
}
