{
  "recipe": {
    "id": "mblock",
    "bundle": "mblock.app",
    "identifier": "cc.mblock",
    "download": "https://dl.makeblock.com/mblock5/darwin/V5.2.0.pkg",
    "sha256": "8a90d4e341b73adff1ff6db704426b6c343e5d2786f8183f5c52ec0240103abf",
    "appcast": {
      "url": "https://www.mblock.cc/mblock-software/",
      "checkpoint": "d7b1d75ca6bcf15083a895dd8221ea3ca24a5a57ca00006b45797c2c3a58ba8f"
    },
    "version": "5.2.0",
    "build": null,
    "dir": "/Applications/Makeblock",
    "symlink": null,
    "web": "https://www.mblock.cc/"
  }
}
