{
  "recipe": {
    "id": "opera",
    "bundle": "Opera.app",
    "identifier": "com.operasoftware.Opera",
    "download": "https://get.geo.opera.com/pub/opera/desktop/57.0.3098.91/mac/Opera_57.0.3098.91_Setup.dmg",
    "sha256": "ba9113fac5cc98f8bb774ede5e2c8de1050f453edd03f875b8e2fed5274b0ed3",
    "appcast": {
        "url": null,
        "checkpoint": null
    },
    "version": null,
    "build": "57.0.3098.91",
    "dir": "/Applications",
    "symlink": null,
    "web": "https://www.opera.com/"
  }
}
