{
  "recipe": {
    "id": "oxfordlearnersbookshelf",
    "bundle": "Oxford Learners Bookshelf.app",
    "identifier": "com.oxfordlearnersbookshelf.ods",
    "download": "https://www.oxfordlearnersbookshelf.com/home/mac/download.html",
    "sha256": "f02f00ef1939718a88e252754ea9e411a5f2f9ccb90ce724127f1d305c3492b3",
    "appcast": {
      "url": null,
      "checkpoint": null
    },
    "version": "5.7.0",
    "build": null,
    "dir": "/Applications",
    "symlink": "/Applications/Lernprogramme/ Lernprogramme starten/English",
    "web": "https://www.oxfordlearnersbookshelf.com/",
    "ci": "true"
  }
}
