{
  "recipe": {
    "id": "packages",
    "bundle": "Packages.app",
    "identifier": "fr.whitebox.Packages",
    "download": "http://s.sudre.free.fr/Software/files/Packages.dmg",
    "sha256": "a24225be6981228f16f17140af2af91c0d27cac82c879de98e6ca788a4591f18",
    "appcast": {
      "url": "http://s.sudre.free.fr/Software/documentation/RemoteVersion.plist",
      "checkpoint": "ad8291130c9b0115ac48d03f0b236989af19058f5aecb8b2ac21d6baf90b46a5"
    },
    "version": "1.2.6",
    "build": null,
    "dir": "/Applications",
    "symlink": null,
    "web": "http://s.sudre.free.fr/Software/Packages/about.html"
  }
}
