{
  "recipe": {
    "id": "plexmediaplayer",
    "bundle": "Plex Media Player.app",
    "identifier": "tv.plex.player",
    "download": "https://downloads.plex.tv/plexmediaplayer/2.14.1.880-301a4b6c/PlexMediaPlayer-2.14.1.880-301a4b6c-macosx-x86_64.zip",
    "sha256": "50bca3314b97530dde4bf6175e63aa50b107e5635863a5b618fb385d9491a4a8",
    "appcast": {
        "url": "https://plex.tv/api/downloads/3.json",
        "checkpoint": "842fa43171938f6a3ab0149ce0937d8dbfbd0384c2ae38ab3002eaed2d30abc3"
    },
    "version": "2.14.1.880-301a4b6c",
    "build": null,
    "dir": "/Applications",
    "symlink": null,
    "web": "https://www.plex.tv/"
  }
}
