{
  "recipe": {
    "id": "pycharmce",
    "bundle": "PyCharm CE.app",
    "identifier": "com.jetbrains.pycharm",
    "download": "https://download.jetbrains.com/python/pycharm-community-2019.2.3.dmg",
    "sha256": "9998175925d99ca2e817461f5ce2823409c8bd2c9579bde2cd20dbba6490906a",
    "appcast": {
      "url": "https://data.services.jetbrains.com/products/releases?code=PCC&latest=true&type=release",
      "checkpoint": "fdb97b0bf6a978fb9cd0d8e2c7a82dfc7fd566a272906172046ff6db566b4158"
    },
    "version": "2019.2.3",
    "build": null,
    "dir": "/Applications",
    "symlink": null,
    "web": "https://www.jetbrains.com/pycharm/"
  }
}
