{
  "recipe": {
    "id": "resiliosync",
    "bundle": "Resilio Sync.app",
    "identifier": "com.resilio.Sync",
    "download": "https://download-cdn.resilio.com/2.7.0/osx/Resilio-Sync.dmg",
    "sha256": "ea7b33283c6993c1d6f2ed3e75ba5743bf014b3a19351f5cfeb6dddd8f8cb842",
    "appcast": {
      "url": "https://help.resilio.com/hc/en-us/articles/206216855-Sync-2-x-change-log",
      "checkpoint": "723dbad9744fdb0c0c8d5294e4e2a7277a487d38639800d5a9f26470f36e86d0"
    },
    "version": "2.7.0",
    "build": null,
    "dir": "/Applications",
    "symlink": null,
    "web": "https://www.resilio.com/"
  }
}
