{
  "recipe": {
    "id": "sketch",
    "bundle": "Sketch.app",
    "identifier": "com.bohemiancoding.sketch3",
    "download": "https://download.sketchapp.com/sketch-52.5-67469.zip",
    "sha256": "a31908295aabb1b8d2c29326dab9c4097e8c3195ecdb4a401c65c1874d7f4f57",
    "appcast": {
        "url": "https://download.sketchapp.com/sketch-versions.xml",
        "checkpoint": "33603138044de36e26fba0d2b3bdaec55036890e6a984bd48184fd47264b5a77"
    },
    "version": "52.5",
    "build": null,
    "dir": "/Applications",
    "symlink": null,
    "web": "https://www.sketchapp.com/"
  }
}
