{
  "recipe": {
    "id": "starface",
    "bundle": "STARFACE UCC Client.app",
    "identifier": "de.starface.STARFACE-Client",
    "download": "https://www.starface-cdn.de/starface/ISOS/STARFACE_UCC_Client_6.7.0.2.zip",
    "sha256": "758a743c2d3dd54b46ef9d9e153a36b7be7b485a5eb14cfcc2f885c59becf201",
    "appcast": {
      "url": "https://knowledge.starface.de/plugins/viewsource/viewpagesrc.action?pageId=6979592",
      "checkpoint": "abee3ad497935dc0d7d7f7ccd4b461c6d5cb640e782bc69ccc794cdeed2c0083"
    },
    "version": "6.7.0.2",
    "build": null,
    "dir": "/Applications",
    "symlink": null,
    "web": "https://www.starface.com/starface/ucc-client/"
  }
}
