{
  "recipe": {
    "id": "thunderbird-en",
    "bundle": "Thunderbird.app",
    "identifier": "org.mozilla.thunderbird",
    "download": "https://ftp.mozilla.org/pub/thunderbird/releases/68.1.2/mac/en-US/Thunderbird%2068.1.2.dmg",
    "sha256": "7b35fe87e8a9c2a150d9521999a330ec24654b819dcfa756c59c701864d9c6f9",
    "appcast": {
      "url": null,
      "checkpoint": null
    },
    "version": "68.1.2",
    "build": null,
    "dir": "/Applications",
    "symlink": null,
    "web": "https://www.mozilla.org/thunderbird/"
  }
}
