{
  "recipe": {
    "id": "thunderbird-en",
    "bundle": "Thunderbird.app",
    "identifier": "org.mozilla.thunderbird",
    "download": "https://download.mozilla.org/?product=thunderbird-latest&os=osx&lang=en-US",
    "sha256": "859d138390c9a73970cdc6b70b69179f04f9740b48967d75993535731981de15",
    "appcast": {
      "url": null,
      "checkpoint": null
    },
    "version": "78.0.1",
    "build": null,
    "dir": "/Applications",
    "symlink": null,
    "web": "https://www.mozilla.org/thunderbird/",
    "ci": "true"
  }
}
