{
  "recipe": {
    "appcast": {
      "checkpoint": null,
      "url": null
    },
    "bundle": "Touché.app",
    "ci": "true",
    "dir": "/Applications",
    "download": "https://aky-assets.s3.eu-central-1.wasabisys.com/Touche-1.1.4.pkg",
    "id": "touche",
    "identifier": "null",
    "internal": "true",
    "processes": null,
    "sha256": "0290874a008a9725f4807e7ec99dbec3959b18518eae4c71f6e29ee559822712",
    "symlink": null,
    "version": "1.1.4",
    "web": "https://red-sweater.com/touche/"
  }
}
