{
  "recipe": {
    "id": "transmit",
    "bundle": "Transmit.app",
    "identifier": "com.panic.Transmit",
    "download": "https://download.panic.com/transmit/Transmit%205.2.1.zip",
    "sha256": "028a9d934288af9b196c3bf8a8b650c948ccbfa055d2b6d451730b8846c0c954",
    "appcast": {
        "url": "https://library.panic.com/releasenotes/transmit5/",
        "checkpoint": "4fd6d5d279186df27ec01e6ccffc23882443dad6be6a6a52150dbff033f79f56"
    },
    "version": "5.2.1",
    "build": null,
    "dir": "/Applications",
    "symlink": null,
    "web": "https://panic.com/transmit/"
  }
}
