{
  "recipe": {
    "id": "ubersicht",
    "bundle": "Übersicht.app",
    "identifier": "tracesOf.Uebersicht",
    "download": "http://tracesof.net/uebersicht/releases/Uebersicht-1.4.60.app.zip",
    "sha256": "f4df9f0dd9b44b0c3159ad3c03086560b605870a413851d1c2036b8090bebc2b",
    "appcast": {
      "url": "http://tracesof.net/uebersicht/updates.xml.rss",
      "checkpoint": "1b6651d14370c52dc70e5359c58396b94af05b3a82394673c96f4ba99dbc6e69"
    },
    "version": null,
    "build": "60",
    "dir": "/Applications",
    "symlink": null,
    "web": "http://tracesof.net/uebersicht/"
  }
}
