{
  "recipe": {
    "appcast": {
      "checkpoint": null,
      "url": null
    },
    "bundle": "Vivaldi.app",
    "ci": "true",
    "dir": "/Applications",
    "download": "https://downloads.vivaldi.com/stable/Vivaldi.4.0.2312.33.universal.dmg",
    "id": "vivaldi",
    "identifier": "com.vivaldi.Vivaldi",
    "processes": [],
    "sha256": "a016dd7dffd611fd1a3df714a2a43cf850d40140662d5bdf35b0b9dbecb26e4f",
    "symlink": null,
    "version": "4.0.2312.33",
    "web": "https://vivaldi.com/"
  }
}
