{
  "recipe": {
    "id": "vncviewer",
    "bundle": "VNC Viewer.app",
    "identifier": "com.realvnc.vncviewer",
    "download": "https://www.realvnc.com/download/file/viewer.files/VNC-Viewer-6.20.113-MacOSX-x86_64.dmg",
    "sha256": "d6035174e9e4aa2e281b49abc953b75c915a1eca9173d56140ddfa3c129197dd",
    "appcast": {
      "url": "https://www.realvnc.com/en/connect/download/viewer/macos/",
      "checkpoint": "b79d75f01a7b67bf3812220b545d95da2ba92a4ec271277095b863e312887dea"
    },
    "version": null,
    "build": "6.20.113.42303",
    "dir": "/Applications",
    "symlink": null,
    "web": "https://www.realvnc.com/"
  }
}
