{
  "recipe": {
    "id": "wireshark",
    "bundle": "Wireshark.app",
    "identifier": "org.wireshark.Wireshark",
    "download": "https://www.wireshark.org/download/osx/Wireshark%203.0.4%20Intel%2064.dmg",
    "sha256": "82e5d5ac1379488e7de40965d68c0f66f50a409ebf1f0b94386d40d8b4b88951",
    "appcast": {
      "url": "https://www.macupdater.net/cgi-bin/extract_text/extract_text_split_easy.cgi?url=https://www.wireshark.org/download.html&splitter_1=stable&index_1=1&splitter_2=development&index_2=0",
      "checkpoint": "d0a2322eef89f0662062da4013ee0a22cde8fa9f9cac889ccc1a84d4816e94e7"
    },
    "version": "3.0.4",
    "build": null,
    "dir": "/Applications",
    "symlink": null,
    "web": "https://www.wireshark.org/"
  }
}
